dgcloud/__init__.py
dgcloud/cli.py
dgcloud/cloud.py
dgcloud-0.1.3.dist-info/LICENSE
dgcloud-0.1.3.dist-info/METADATA
dgcloud-0.1.3.dist-info/WHEEL
dgcloud-0.1.3.dist-info/entry_points.txt
dgcloud-0.1.3.dist-info/top_level.txt
dgcloud-0.1.3.dist-info/RECORD
