Metadata-Version: 2.1
Name: dgcloud
Version: 0.1.3
Summary: UNKNOWN
Home-page: https://github.com/Dhinagaran-s/dgcloud
Author: Dhinagaran (Dg)
Author-email: dhinagaran1411@gmail.com
License: UNKNOWN
Platform: UNKNOWN
License-File: LICENSE
Requires-Dist: click
Requires-Dist: paramiko
Requires-Dist: pyyaml
